ndexgenehancerloader/__init__.py
ndexgenehancerloader/genetypes.json
ndexgenehancerloader/loadplan.json
ndexgenehancerloader/ndexloadgenehancer.py
ndexgenehancerloader/style.cx
ndexgenehancerloader-0.1.0.data/scripts/ndexloadgenehancer.py
ndexgenehancerloader-0.1.0.dist-info/AUTHORS.rst
ndexgenehancerloader-0.1.0.dist-info/LICENSE
ndexgenehancerloader-0.1.0.dist-info/METADATA
ndexgenehancerloader-0.1.0.dist-info/WHEEL
ndexgenehancerloader-0.1.0.dist-info/top_level.txt
ndexgenehancerloader-0.1.0.dist-info/RECORD
