Metadata-Version: 2.1
Name: ndexgenehancerloader
Version: 0.1.0
Summary: Loads GeneHancer database to NDEx
Home-page: https://github.com/ceofy/ndexgenehancerloader
Author: Sophie Liu
Author-email: sol015@ucsd.edu
License: MIT license
Keywords: ndexgenehancerloader
Platform: UNKNOWN
Classifier: Development Status :: 2 - Pre-Alpha
Classifier: Intended Audience :: Developers
Classifier: License :: OSI Approved :: MIT License
Classifier: Natural Language :: English
Classifier: Programming Language :: Python :: 3.4
Classifier: Programming Language :: Python :: 3.5
Classifier: Programming Language :: Python :: 3.6
Classifier: Programming Language :: Python :: 3.7
Requires-Dist: ndex2
Requires-Dist: ndexutil
